spadsim/__init__.py
spadsim/scheduler.py
spadsim/simulator.py
spadsim-0.1.0.dist-info/WHEEL
spadsim-0.1.0.dist-info/METADATA
spadsim-0.1.0.dist-info/RECORD
